pybgworker/__init__.py
pybgworker/backends.py
pybgworker/cancel.py
pybgworker/cli.py
pybgworker/config.py
pybgworker/failed.py
pybgworker/inspect.py
pybgworker/logger.py
pybgworker/purge.py
pybgworker/queue.py
pybgworker/ratelimit.py
pybgworker/result.py
pybgworker/retry.py
pybgworker/scheduler.py
pybgworker/sqlite_queue.py
pybgworker/state.py
pybgworker/stats.py
pybgworker/task.py
pybgworker/utils.py
pybgworker/worker.py
pybgworker-0.2.1.dist-info/licenses/LICENSE
pybgworker-0.2.1.dist-info/METADATA
pybgworker-0.2.1.dist-info/WHEEL
pybgworker-0.2.1.dist-info/entry_points.txt
pybgworker-0.2.1.dist-info/top_level.txt
pybgworker-0.2.1.dist-info/RECORD
