Metadata-Version: 2.4
Name: pybgworker
Version: 0.2.1
Summary: Lightweight production-ready background task worker with cron, rate limiting and JSON observability
Author: Prabhat Verma
License: MIT
Project-URL: Homepage, https://github.com/prabhat708/pybgworker
Project-URL: Repository, https://github.com/prabhat708/pybgworker
Project-URL: Issues, https://github.com/prabhat708/pybgworker/issues
Keywords: background-jobs,task-queue,sqlite,cron,worker,job-queue
Classifier: Development Status :: 5 - Production/Stable
Classifier: Intended Audience :: Developers
Classifier: License :: OSI Approved :: MIT License
Classifier: Programming Language :: Python :: 3
Classifier: Programming Language :: Python :: 3.8
Classifier: Programming Language :: Python :: 3.9
Classifier: Programming Language :: Python :: 3.10
Classifier: Programming Language :: Python :: 3.11
Classifier: Operating System :: OS Independent
Requires-Python: >=3.8
License-File: LICENSE
Requires-Dist: croniter>=1.4.0
Dynamic: license-file
